doodl/__init__.py
doodl/__main__.py
doodl/data.py
doodl/doodl.py
doodl/requirements.txt
doodl/tests/__init__.py
doodl/tests/test_doodl.py
doodl-0.8.1.dist-info/entry_points.txt
doodl-0.8.1.dist-info/licenses/LICENSE
doodl-0.8.1.dist-info/WHEEL
doodl-0.8.1.dist-info/METADATA
doodl-0.8.1.dist-info/RECORD
