Metadata-Version: 2.4
Name: doodl
Version: 0.8.1
Summary: A python module for including beautiful charts in Markdown for conversion to HTML
Author-email: "doodl.ai" <info@doodl.ai>
Requires-Python: >=3.7
License-File: LICENSE
Requires-Dist: pypandoc
Requires-Dist: beautifulsoup4
Requires-Dist: seaborn
Requires-Dist: colorcet
Requires-Dist: playwright
Requires-Dist: requests
Requires-Dist: ipython
